illallangi/data/air_transport/__init__.py
illallangi/data/air_transport/__version__.py
illallangi/data/air_transport/apps.py
illallangi/data/air_transport/adapters/__init__.py
illallangi/data/air_transport/adapters/air_transport.py
illallangi/data/air_transport/admin/__init__.py
illallangi/data/air_transport/admin/flight.py
illallangi/data/air_transport/admin/trip.py
illallangi/data/air_transport/checks/__init__.py
illallangi/data/air_transport/checks/air_transport.py
illallangi/data/air_transport/checks/tripit.py
illallangi/data/air_transport/diffsyncmodels/__init__.py
illallangi/data/air_transport/diffsyncmodels/flight.py
illallangi/data/air_transport/diffsyncmodels/trip.py
illallangi/data/air_transport/migrations/0001_initial.py
illallangi/data/air_transport/migrations/__init__.py
illallangi/data/air_transport/models/__init__.py
illallangi/data/air_transport/models/flight.py
illallangi/data/air_transport/models/trip.py
illallangi/data/air_transport/static/air_transport/barcode.png
illallangi/data/air_transport/static/air_transport/flight.css
illallangi/data/air_transport/static/air_transport/flights.jpg
illallangi/data/air_transport/static/air_transport/routes.jpg
illallangi/data/air_transport/static/air_transport/trips.jpg
illallangi/data/air_transport/templates/air_transport/flight_detail.html
illallangi/data/air_transport/templates/air_transport/flight_list.html
illallangi/data/air_transport/templates/air_transport/trip_detail.html
illallangi/data/air_transport/templates/air_transport/trip_list.html
illallangi/data/air_transport/views/__init__.py
illallangi/data/air_transport/views/flight_detail.py
illallangi/data/air_transport/views/flight_list.py
illallangi/data/air_transport/views/trip_detail.py
illallangi/data/air_transport/views/trip_list.py
illallangi_data_air_transport-0.4.1.dist-info/METADATA
illallangi_data_air_transport-0.4.1.dist-info/WHEEL
illallangi_data_air_transport-0.4.1.dist-info/entry_points.txt
illallangi_data_air_transport-0.4.1.dist-info/licenses/LICENSE
illallangi_data_air_transport-0.4.1.dist-info/RECORD
