Metadata-Version: 2.3
Name: illallangi-data-air-transport
Version: 0.4.1
Summary: An Illallangi Data plugin for recording air transport data.
Project-URL: Homepage, https://github.com/illallangi/data-air-transport
Project-URL: Repository, https://github.com/illallangi/data-air-transport.git
Project-URL: Issues, https://github.com/illallangi/data-air-transport/issues
Project-URL: Changelog, https://github.com/illallangi/data-air-transport/blob/master/CHANGELOG.md
Author-email: Andrew Cole <andrew.cole@illallangi.com>
Maintainer-email: Andrew Cole <andrew.cole@illallangi.com>
License: MIT License
License-File: LICENSE
Keywords: data,data-lake,django
Classifier: Development Status :: 3 - Alpha
Classifier: Intended Audience :: Developers
Classifier: License :: OSI Approved :: MIT License
Classifier: Programming Language :: Python :: 3.12
Requires-Python: >=3.10.1
Requires-Dist: diffsync>=2.0.0
Requires-Dist: django-autoslug>=1.9.9
Requires-Dist: django-timezone-field>=7.0
Requires-Dist: django>=5.1.2
Requires-Dist: djp
Requires-Dist: illallangi-data-aviation>=0.4.0
Requires-Dist: illallangi-tripit>=0.8.0
